AutoFlask/AutoFlask.py
AutoFlask/__init__.py
AutoFL-1.3.dist-info/LICENSE
AutoFL-1.3.dist-info/METADATA
AutoFL-1.3.dist-info/WHEEL
AutoFL-1.3.dist-info/entry_points.txt
AutoFL-1.3.dist-info/top_level.txt
AutoFL-1.3.dist-info/RECORD
