Metadata-Version: 2.1
Name: AutoFL
Version: 1.3
Summary: AutoFlask simplifies Flask project setup, automating the creation of essential files and directories with just one command.
Home-page: https://github.com/OwenOrcan/AutoFlask
Author: Owen Orcan
Author-email: owenorcan@gmail.com
License: MIT License
License-File: LICENSE
